pytext/__init__.py
pytext/utils.py
pytext/vocab.py
pytext/data/__init__.py
pytext/data/batch.py
pytext/data/dataset.py
pytext/data/datasetbase.py
pytext/data/example.py
pytext/data/field.py
pytext/data/iterator.py
pytext/data/pipeline.py
pytext/data/utils.py
pytext/datasets/__init__.py
pytext/datasets/babi.py
pytext/datasets/imdb.py
pytext/datasets/language_modeling.py
pytext/datasets/sequence_tagging.py
pytext/datasets/snli.py
pytext/datasets/sst.py
pytext/datasets/translation.py
pytext/datasets/trec.py
pytexttool-0.3.1.dist-info/DESCRIPTION.rst
pytexttool-0.3.1.dist-info/METADATA
pytexttool-0.3.1.dist-info/RECORD
pytexttool-0.3.1.dist-info/WHEEL
pytexttool-0.3.1.dist-info/metadata.json
pytexttool-0.3.1.dist-info/top_level.txt
pytexttool-0.3.1.dist-info/zip-safe
test/common/__init__.py
test/common/pytext_test_case.py
test/common/test_markers.py
test/data/__init__.py
test/data/test_batch.py
test/data/test_builtin_datasets.py
test/data/test_dataset.py
test/data/test_field.py
test/data/test_pipeline.py
test/data/test_subword.py
test/data/test_utils.py
