Metadata-Version: 2.0
Name: pytexttool
Version: 0.3.1
Summary: Text utilities and datasets for generic deep learning, Fork from torchtext but uses numpy to store datasets for more generic use.
Home-page: https://github.com/iclementine/text
Author: Clementine
Author-email: iclementine@outlook.com
License: BSD
Platform: UNKNOWN
Requires-Dist: requests
Requires-Dist: tqdm
